oracle_cpq_ui_automation/__init__.py
oracle_cpq_ui_automation/bmllib.py
oracle_cpq_ui_automation/partner_orgs.py
py_oracle_cpq_ui_automation-1.0.3.dist-info/LICENSE
py_oracle_cpq_ui_automation-1.0.3.dist-info/METADATA
py_oracle_cpq_ui_automation-1.0.3.dist-info/WHEEL
py_oracle_cpq_ui_automation-1.0.3.dist-info/top_level.txt
py_oracle_cpq_ui_automation-1.0.3.dist-info/RECORD
