Metadata-Version: 2.1
Name: py-oracle-cpq-ui-automation
Version: 1.0.3
Summary: Selenium based automation on Oracle CPQ UI
Home-page: https://github.com/arunkumar-js25/oracle_cpq_ui_automation
Author-email: arunkumar.js25@gmail.com
License: UNKNOWN
Keywords: automation,oracle,oracle cpq
Platform: UNKNOWN
Classifier: License :: OSI Approved :: MIT License
Classifier: Intended Audience :: Developers
Classifier: Programming Language :: Python :: 3 :: Only
License-File: LICENSE
